hdp_toolchain-0.8.8.6.post1-py3.8-nspkg.pth
hxlm/core/__init__.py
hxlm/core/compliance.py
hxlm/core/constant.py
hxlm/core/exception.py
hxlm/core/hxl.py
hxlm/core/util.py
hxlm/core/_dt/__init__.py
hxlm/core/_dt/test.py
hxlm/core/bin/__init__.py
hxlm/core/bin/cor.hxltm.yml
hxlm/core/bin/hdpcli.py
hxlm/core/bin/hdplisp-cli.js
hxlm/core/bin/hxl2tab.py
hxlm/core/bin/hxlquickimport.py
hxlm/core/bin/hxlquickmeta.py
hxlm/core/bin/hxltmcli.py
hxlm/core/bin/hxltmdexml.py
hxlm/core/bin/servitium.urn.yml
hxlm/core/bin/urnprovider_local.py
hxlm/core/bin/urnresolver-default.urn.yml
hxlm/core/bin/urnresolver.py
hxlm/core/hdp/__init__.py
hxlm/core/hdp/exception.py
hxlm/core/hdp/index.py
hxlm/core/hdp/item.py
hxlm/core/hdp/project.py
hxlm/core/hdp/raw.py
hxlm/core/hdp/hazmat/check.py
hxlm/core/hdp/hazmat/data.py
hxlm/core/hdp/hazmat/policy.py
hxlm/core/hdp/hazmat/rule.py
hxlm/core/hdp/util/__init__.py
hxlm/core/hdp/util/common.py
hxlm/core/hdp/util/debug.py
hxlm/core/hdp/util/l10n.py
hxlm/core/htype/__init__.py
hxlm/core/htype/actor.py
hxlm/core/htype/compliance.py
hxlm/core/htype/data.py
hxlm/core/htype/encryption.py
hxlm/core/htype/level.py
hxlm/core/htype/license.py
hxlm/core/htype/routing.py
hxlm/core/htype/sensitive.py
hxlm/core/htype/storage.py
hxlm/core/htype/urn.py
hxlm/core/htype/usage.py
hxlm/core/htype/weight.py
hxlm/core/internal/__init__.py
hxlm/core/internal/formatter.py
hxlm/core/internal/integrity.py
hxlm/core/internal/keystore.py
hxlm/core/internal/util.py
hxlm/core/io/__init__.py
hxlm/core/io/cache.py
hxlm/core/io/converter.py
hxlm/core/io/hxl.py
hxlm/core/io/local.py
hxlm/core/io/net.py
hxlm/core/io/s3.py
hxlm/core/io/ssh.py
hxlm/core/io/util.py
hxlm/core/localization/__init__.py
hxlm/core/localization/hgettext.py
hxlm/core/localization/util.py
hxlm/core/localization/translation/__init__.py
hxlm/core/localization/translation/interactive.py
hxlm/core/localization/translation/machine.py
hxlm/core/localization/translation/memory.py
hxlm/core/model/__init__.py
hdp_toolchain-0.8.8.6.post1.dist-info/METADATA
hdp_toolchain-0.8.8.6.post1.dist-info/WHEEL
hdp_toolchain-0.8.8.6.post1.dist-info/entry_points.txt
hdp_toolchain-0.8.8.6.post1.dist-info/namespace_packages.txt
hdp_toolchain-0.8.8.6.post1.dist-info/top_level.txt
hdp_toolchain-0.8.8.6.post1.dist-info/RECORD
