Metadata-Version: 2.1
Name: hdp-toolchain
Version: 0.8.8.6.post1
Summary: HDP Declarative Programming toolchain
Home-page: https://github.com/EticaAI/HXL-Data-Science-file-formats
Author: Emerson Rocha
Author-email: rocha@ieee.org
License: UNKNOWN
Project-URL: Bug Tracker, https://github.com/EticaAI/HXL-Data-Science-file-formats/issues
Platform: UNKNOWN
Classifier: Programming Language :: Python :: 3
Classifier: License :: OSI Approved :: The Unlicense (Unlicense)
Classifier: Operating System :: OS Independent
Classifier: Topic :: Scientific/Engineering :: Artificial Intelligence
Classifier: Typing :: Typed
Classifier: Topic :: Utilities
Requires-Python: >=3.7
Requires-Dist: libhxl
Requires-Dist: pygments
Requires-Dist: pyyaml
Requires-Dist: langcodes
Requires-Dist: python-liquid
Provides-Extra: full
Requires-Dist: hug ; extra == 'full'
Requires-Dist: slugify ; extra == 'full'
Requires-Dist: cryptography ; extra == 'full'
Requires-Dist: keyring ; extra == 'full'
Provides-Extra: hxl2tab
Requires-Dist: hug ; extra == 'hxl2tab'
Provides-Extra: hxlquickimport
Requires-Dist: hug ; extra == 'hxlquickimport'
Requires-Dist: slugify ; extra == 'hxlquickimport'
Provides-Extra: hxlquickmeta
Requires-Dist: hug ; extra == 'hxlquickmeta'
Requires-Dist: pandas ; extra == 'hxlquickmeta'
Requires-Dist: Orange3 ; extra == 'hxlquickmeta'
Provides-Extra: hxltm
Requires-Dist: defusedxml ; extra == 'hxltm'
Provides-Extra: hxltmcli
Requires-Dist: cryptography ; extra == 'hxltmcli'
Requires-Dist: keyring ; extra == 'hxltmcli'
Provides-Extra: urnresolver
